gpumux/__init__.py
gpumux/gpumux.py
gpumux/templates/home.html
gpumux-1.0.1.dist-info/METADATA
gpumux-1.0.1.dist-info/RECORD
gpumux-1.0.1.dist-info/WHEEL
gpumux-1.0.1.dist-info/entry_points.txt
gpumux-1.0.1.dist-info/top_level.txt
